hfortix_core/__init__.py
hfortix_core/__init__.pyi
hfortix_core/cache.py
hfortix_core/deprecation.py
hfortix_core/exceptions.py
hfortix_core/fmt.py
hfortix_core/py.typed
hfortix_core/types.py
hfortix_core/audit/__init__.py
hfortix_core/audit/base.py
hfortix_core/audit/formatters.py
hfortix_core/audit/handlers.py
hfortix_core/debug/__init__.py
hfortix_core/debug/base.py
hfortix_core/debug/formatters.py
hfortix_core/debug/handlers.py
hfortix_core/hooks/__init__.py
hfortix_core/http/__init__.py
hfortix_core/http/async_client.py
hfortix_core/http/async_client.pyi
hfortix_core/http/base.py
hfortix_core/http/client.py
hfortix_core/http/client.pyi
hfortix_core/http/fmg_client.py
hfortix_core/http/fmg_client.pyi
hfortix_core/http/interface.py
hfortix_core/logging/__init__.py
hfortix_core/logging/base.py
hfortix_core/logging/formatters.py
hfortix_core/logging/handlers.py
hfortix_core/utils/__init__.py
hfortix_core-0.5.148.dist-info/METADATA
hfortix_core-0.5.148.dist-info/WHEEL
hfortix_core-0.5.148.dist-info/top_level.txt
hfortix_core-0.5.148.dist-info/RECORD
