Metadata-Version: 2.4
Name: hfortix-core
Version: 0.5.148
Summary: Core foundation for HFortix - Fortinet SDK
Author-email: "Herman W. Jacobsen" <herman@wjacobsen.fo>
License: Proprietary
Project-URL: Homepage, https://github.com/hermanwjacobsen/hfortix
Project-URL: Repository, https://github.com/hermanwjacobsen/hfortix
Keywords: fortinet,fortigate,fortios,api,sdk
Classifier: Development Status :: 4 - Beta
Classifier: Intended Audience :: Developers
Classifier: Programming Language :: Python :: 3
Classifier: Programming Language :: Python :: 3.10
Classifier: Programming Language :: Python :: 3.11
Classifier: Programming Language :: Python :: 3.12
Requires-Python: >=3.10
Requires-Dist: httpx[http2]>=0.27.0
Requires-Dist: typing_extensions>=4.0.0
